example_tjc/__init__.py
example_tjc/main.py
example_tjc-0.0.0.dev2.dist-info/METADATA
example_tjc-0.0.0.dev2.dist-info/WHEEL
example_tjc-0.0.0.dev2.dist-info/licenses/LICENSE
example_tjc-0.0.0.dev2.dist-info/RECORD
