Metadata-Version: 2.4
Name: example-tjc
Version: 0.0.0.dev2
Summary: Add a description here
Project-URL: Homepage, https://github.com/threejeanchilli/example-pypi
License-File: LICENSE
Requires-Python: >=3.10
